{"category": "", "head": {"release": false, "meta_version": "1.0", "auto_write": true, "script_language": "R", "script_environment": "clarity"}, "description": "Description for gxcdhvgq_xovfkb_ofrdl", "title": "gxcdhvgq_xovfkb_ofrdl", "closing_date": "%monthly_closing%", "transaction_start_date": "%monthly_closing%-P2M->first", "dependencies_list": [], "transaction_end_date": "%monthly_closing%->last", "keywords": "madrid,store", "class": "merchantsES", "columns": {"tags": [], "names": [], "descriptions": []}, "name": "gxcdhvgq_xovfkb_ofrdl"}