{"category": "c3_1", "head": {"release": false, "meta_version": "1.0", "auto_write": true, "script_language": "R", "script_environment": "clarity"}, "description": "Description for voftzacd_neqfjo", "title": "voftzacd_neqfjo", "closing_date": "%monthly_closing%", "transaction_start_date": "%monthly_closing%-P2M->first", "dependencies_list": [], "transaction_end_date": "%monthly_closing%->last", "keywords": "football,store", "class": "cli0182", "columns": {"tags": [], "names": [], "descriptions": []}, "name": "voftzacd_neqfjo"}